{
  "schemaVersion": 1,
  "id": "essential_commands",
  "version": "${version}",

  "name": "Essential Commands",
  "description": "Various commands to improve your minecraft experience!",
  "authors": [
    "John Paul R. (JP79194)"
  ],
  "contact": {
    "homepage": "https://fabricmc.net/",
    "sources": "https://github.com/FabricMC/fabric-example-mod"
  },

  "license": "CC0-1.0",
  "icon": "assets/essential_commands/icon.png",

  "environment": "*",
  "entrypoints": {
    "main": [
      "com.fibermc.essentialcommands.EssentialCommands"
    ]
  },
  "mixins": [
    "essential_commands.mixins.json"
  ],

  "depends": {
    "fabricloader": ">=0.4.0",
    "fabric": "*"
  },
  "suggests": {
    "flamingo": "*"
  }
}
